discord_joiner/__init__.py
discord_joiner/_resources.py
discord_joiner/exceptions.py
discord_joiner/joiner.py
discord_joiner_deskent-1.0.17.dist-info/LICENSE
discord_joiner_deskent-1.0.17.dist-info/METADATA
discord_joiner_deskent-1.0.17.dist-info/WHEEL
discord_joiner_deskent-1.0.17.dist-info/top_level.txt
discord_joiner_deskent-1.0.17.dist-info/RECORD
