Metadata-Version: 2.1
Name: discord-joiner-deskent
Version: 1.0.17
Summary: Discord accounts joiner
Author: Deskent
Author-email: battenetciz@gmail.com
Classifier: License :: OSI Approved :: MIT License
Classifier: Programming Language :: Python
Classifier: Programming Language :: Python :: 3
Classifier: Operating System :: OS Independent
Requires-Python: >=3.7
License-File: LICENSE
Requires-Dist: python-dotenv (==0.19.2)
Requires-Dist: requests (==2.27.1)
Requires-Dist: myloguru-deskent (==0.1.1)
